LICENSE
MANIFEST.in
README.md
changelog.md
pyproject.toml
pytest.ini
setup.cfg
setup.py
rpforest/VERSION
rpforest/__init__.py
rpforest/rpforest.py
rpforest/rpforest_fast.cpp
rpforest/rpforest_fast.pyx
rpforest.egg-info/PKG-INFO
rpforest.egg-info/SOURCES.txt
rpforest.egg-info/dependency_links.txt
rpforest.egg-info/requires.txt
rpforest.egg-info/top_level.txt
tests/rpforest_v1.pickle
tests/test_rpforest.py