Metadata-Version: 2.1
Name: rpforest
Version: 1.6
Summary: Random Projection Forest for approximate nearest neighbours search.
Home-page: https://github.com/lyst/rpforest
Author: LYST Ltd (Maciej Kula)
Author-email: data@lyst.com
License: Apache 2.0
Download-URL: https://github.com/lyst/rpforest/tarball/1.6
Project-URL: Source, https://github.com/lyst/rpforest
Platform: UNKNOWN
Classifier: Development Status :: 3 - Alpha
Classifier: License :: OSI Approved :: Apache Software License
Classifier: Programming Language :: Python :: 2
Classifier: Programming Language :: Python :: 2.7
Classifier: Programming Language :: Python :: 3
Classifier: Programming Language :: Python :: 3.5
Classifier: Programming Language :: Python :: 3.6
Classifier: Programming Language :: Python :: 3.7
Classifier: Programming Language :: Python :: 3.8
Requires-Python: >=2.7, !=3.0.*, !=3.1.*, !=3.2.*, !=3.3.*, !=3.4.*
